<annotation>
    <folder>images</folder>
    <filename>135472_149391.jpg</filename>
    <size>
        <width>3456</width>
        <height>4608</height>
        <depth>3</depth>
    </size>
    <object>
        <name>Bar</name>
        <difficult>0</difficult>
        <bndbox>
            <xmin>1957.599976</xmin>
            <ymin>1210.782349</ymin>
            <xmax>2400.777344</xmax>
            <ymax>3580.059082</ymax>
        </bndbox>
    </object>
    <object>
        <name>Bar</name>
        <difficult>0</difficult>
        <bndbox>
            <xmin>935.819336</xmin>
            <ymin>1367.692017</ymin>
            <xmax>1392.583618</xmax>
            <ymax>3545.037598</ymax>
        </bndbox>
    </object>
    <object>
        <name>End</name>
        <difficult>0</difficult>
        <bndbox>
            <xmin>2327.807373</xmin>
            <ymin>2225.135254</ymin>
            <xmax>2763.726318</xmax>
            <ymax>2383.642334</ymax>
        </bndbox>
    </object>
    <object>
        <name>Start</name>
        <difficult>0</difficult>
        <bndbox>
            <xmin>499.738800</xmin>
            <ymin>2217.673828</ymin>
            <xmax>968.007690</xmax>
            <ymax>2416.439697</ymax>
        </bndbox>
    </object>
    <object>
        <name>Barcode</name>
        <difficult>0</difficult>
        <bndbox>
            <xmin>502.205505</xmin>
            <ymin>1202.653931</ymin>
            <xmax>2764.939453</xmax>
            <ymax>3584.709961</ymax>
        </bndbox>
    </object>
</annotation>