<annotation>
    <folder>images</folder>
    <filename>18010_501871.jpg</filename>
    <size>
        <width>3024</width>
        <height>4032</height>
        <depth>3</depth>
    </size>
    <object>
        <name>Bar</name>
        <difficult>0</difficult>
        <bndbox>
            <xmin>348.853729</xmin>
            <ymin>2298.655762</ymin>
            <xmax>2207.234619</xmax>
            <ymax>2648.679199</ymax>
        </bndbox>
    </object>
    <object>
        <name>Bar</name>
        <difficult>0</difficult>
        <bndbox>
            <xmin>417.175537</xmin>
            <ymin>1425.313843</ymin>
            <xmax>2206.827637</xmax>
            <ymax>1713.962646</ymax>
        </bndbox>
    </object>
    <object>
        <name>End</name>
        <difficult>0</difficult>
        <bndbox>
            <xmin>1309.126831</xmin>
            <ymin>2481.611328</ymin>
            <xmax>1568.349731</xmax>
            <ymax>3359.146484</ymax>
        </bndbox>
    </object>
    <object>
        <name>Start</name>
        <difficult>0</difficult>
        <bndbox>
            <xmin>1267.571167</xmin>
            <ymin>871.316711</ymin>
            <xmax>1426.911987</xmax>
            <ymax>1505.848755</ymax>
        </bndbox>
    </object>
    <object>
        <name>Barcode</name>
        <difficult>0</difficult>
        <bndbox>
            <xmin>340.698303</xmin>
            <ymin>875.031799</ymin>
            <xmax>2205.430176</xmax>
            <ymax>3361.888672</ymax>
        </bndbox>
    </object>
</annotation>