<annotation>
    <folder>images</folder>
    <filename>416159_688747_444775.jpg</filename>
    <size>
        <width>3456</width>
        <height>4608</height>
        <depth>3</depth>
    </size>
    <object>
        <name>Bar</name>
        <difficult>0</difficult>
        <bndbox>
            <xmin>2079.357910</xmin>
            <ymin>918.133545</ymin>
            <xmax>2744.558838</xmax>
            <ymax>4085.324707</ymax>
        </bndbox>
    </object>
    <object>
        <name>Bar</name>
        <difficult>0</difficult>
        <bndbox>
            <xmin>1331.947388</xmin>
            <ymin>901.229126</ymin>
            <xmax>1947.854492</xmax>
            <ymax>4028.141602</ymax>
        </bndbox>
    </object>
    <object>
        <name>Bar</name>
        <difficult>0</difficult>
        <bndbox>
            <xmin>534.029968</xmin>
            <ymin>900.622559</ymin>
            <xmax>1165.101318</xmax>
            <ymax>3989.419678</ymax>
        </bndbox>
    </object>
    <object>
        <name>End</name>
        <difficult>0</difficult>
        <bndbox>
            <xmin>2424.008789</xmin>
            <ymin>2375.655273</ymin>
            <xmax>2970.908936</xmax>
            <ymax>2509.412842</ymax>
        </bndbox>
    </object>
    <object>
        <name>Start</name>
        <difficult>0</difficult>
        <bndbox>
            <xmin>217.200348</xmin>
            <ymin>2233.910889</ymin>
            <xmax>679.363220</xmax>
            <ymax>2422.121826</ymax>
        </bndbox>
    </object>
    <object>
        <name>Barcode</name>
        <difficult>0</difficult>
        <bndbox>
            <xmin>212.550003</xmin>
            <ymin>894.819458</ymin>
            <xmax>2970.929199</xmax>
            <ymax>4094.848633</ymax>
        </bndbox>
    </object>
</annotation>