<annotation>
    <folder>images</folder>
    <filename>507323_686008_404107_748594_532261_383400_188334.jpg</filename>
    <size>
        <width>2678</width>
        <height>1507</height>
        <depth>3</depth>
    </size>
    <object>
        <name>Bar</name>
        <difficult>0</difficult>
        <bndbox>
            <xmin>2402.372559</xmin>
            <ymin>307.473114</ymin>
            <xmax>2509.364990</xmax>
            <ymax>898.177734</ymax>
        </bndbox>
    </object>
    <object>
        <name>Bar</name>
        <difficult>0</difficult>
        <bndbox>
            <xmin>2168.388916</xmin>
            <ymin>348.051575</ymin>
            <xmax>2306.629395</xmax>
            <ymax>931.438354</ymax>
        </bndbox>
    </object>
    <object>
        <name>Bar</name>
        <difficult>0</difficult>
        <bndbox>
            <xmin>1807.421387</xmin>
            <ymin>281.292023</ymin>
            <xmax>1947.307373</xmax>
            <ymax>866.654297</ymax>
        </bndbox>
    </object>
    <object>
        <name>Bar</name>
        <difficult>0</difficult>
        <bndbox>
            <xmin>1348.465332</xmin>
            <ymin>300.255280</ymin>
            <xmax>1524.958496</xmax>
            <ymax>905.741455</ymax>
        </bndbox>
    </object>
    <object>
        <name>Bar</name>
        <difficult>0</difficult>
        <bndbox>
            <xmin>960.478760</xmin>
            <ymin>327.404968</ymin>
            <xmax>1103.394165</xmax>
            <ymax>889.022766</ymax>
        </bndbox>
    </object>
    <object>
        <name>Bar</name>
        <difficult>0</difficult>
        <bndbox>
            <xmin>526.304321</xmin>
            <ymin>346.614105</ymin>
            <xmax>693.516846</xmax>
            <ymax>1001.641602</ymax>
        </bndbox>
    </object>
    <object>
        <name>Bar</name>
        <difficult>0</difficult>
        <bndbox>
            <xmin>192.755814</xmin>
            <ymin>312.738556</ymin>
            <xmax>325.829224</xmax>
            <ymax>955.144287</ymax>
        </bndbox>
    </object>
    <object>
        <name>End</name>
        <difficult>0</difficult>
        <bndbox>
            <xmin>2502.275635</xmin>
            <ymin>543.433655</ymin>
            <xmax>2658.677490</xmax>
            <ymax>628.733643</ymax>
        </bndbox>
    </object>
    <object>
        <name>Start</name>
        <difficult>0</difficult>
        <bndbox>
            <xmin>23.559507</xmin>
            <ymin>538.068298</ymin>
            <xmax>208.126114</xmax>
            <ymax>662.263306</ymax>
        </bndbox>
    </object>
    <object>
        <name>Barcode</name>
        <difficult>0</difficult>
        <bndbox>
            <xmin>23.613329</xmin>
            <ymin>280.861572</ymin>
            <xmax>2659.561768</xmax>
            <ymax>1003.163513</ymax>
        </bndbox>
    </object>
</annotation>